README.rst
setup.py
ucnum
ucnum.py
ucnum.egg-info/PKG-INFO
ucnum.egg-info/SOURCES.txt
ucnum.egg-info/dependency_links.txt
ucnum.egg-info/requires.txt
ucnum.egg-info/top_level.txt