Metadata-Version: 1.1
Name: ucnum
Version: 1.1
Summary: Unicode helper and search utility
Home-page: http://github.com/flying-sheep/ucnum
Author: Philipp A.
Author-email: flying-sheep@web.de
License: GPL
Keywords: unicode
Platform: UNKNOWN
Classifier: Topic :: Utilities
Classifier: Environment :: Console
Classifier: Intended Audience :: Developers
Classifier: Programming Language :: Python :: 3
Classifier: Programming Language :: Python :: 3.4
Classifier: Development Status :: 5 - Production/Stable
Classifier: License :: OSI Approved :: GNU General Public License v3 or later (GPLv3+)
